cqase/__init__.py
cqase/api/__init__.py
cqase/api/attachments.py
cqase/api/cases.py
cqase/api/custom_fields.py
cqase/api/defects.py
cqase/api/environments.py
cqase/api/milestones.py
cqase/api/plans.py
cqase/api/projects.py
cqase/api/results.py
cqase/api/runs.py
cqase/api/search.py
cqase/api/shared_steps.py
cqase/api/suites.py
cqase/client.py
cqase/common/__init__.py
cqase/common/base.py
cqase/common/file_type.py
cqase/models.py
cqase/request.py
cqase_client-0.1.3.dist-info/LICENSE
cqase_client-0.1.3.dist-info/WHEEL
cqase_client-0.1.3.dist-info/METADATA
cqase_client-0.1.3.dist-info/RECORD
