Metadata-Version: 2.1
Name: cqase-client
Version: 0.1.3
Summary: Custom qase client
Home-page: https://github.com/berpress/custom-qase-client
Author: alexanderlozovoy
Author-email: berpress@gmail.com
Requires-Python: >=3.8,<4.0
Classifier: Programming Language :: Python :: 3
Classifier: Programming Language :: Python :: 3.10
Classifier: Programming Language :: Python :: 3.8
Classifier: Programming Language :: Python :: 3.9
Requires-Dist: install (>=1.3.5,<2.0.0)
Requires-Dist: pip (>=22.1.2,<23.0.0)
Requires-Dist: requests (>=2.28.1,<3.0.0)
Project-URL: Repository, https://github.com/berpress/custom-qase-client
